Metadata-Version: 2.1
Name: jamburger
Version: 0.1.0
Summary: My first Python library
Home-page: UNKNOWN
Author: Jam-Burger
License: MIT
Platform: UNKNOWN
